parsers/__init__.py
parsers/exceptions.py
parsers/fields.py
parsers/manager.py
parsers/parser.py
parsers/translators.py
ghostparser-0.15.dist-info/METADATA
ghostparser-0.15.dist-info/WHEEL
ghostparser-0.15.dist-info/top_level.txt
ghostparser-0.15.dist-info/RECORD
